[
  {
    "rollNo": 1,
    "name": "Mukul Sharma",
    "phone": "8287901366",
    "email": "mukul.sharma@gmail.com",
    "scores": {
      "Solutions": 0,
      "Electrochemistry": 0,
      "Chemical Kinetics": 0,
      "d- and f-Block": 0,
      "Coordination Compounds": 0,
      "Haloalkanes and Haloarenes": 0,
      "Alcohols Phenols and Ethers": 0,
      "Aldehydes Ketones and Carboxylic Acids": 0,
      "Amines": 0,
      "Biomolecules": 0,
      "Electrostatics": 0,
      "Current Electricity": 0,
      "Magnetic Effects of Current": 0,
      "Electromagnetic Induction and AC": 0,
      "Electromagnetic Waves": 0,
      "Ray Optics and Optical Instruments": 0,
      "Wave Optics": 0,
      "Dual Nature of Matter": 0,
      "Atoms and Nuclei": 0,
      "Electronic Devices": 0,
      "Relations and Functions": 0,
      "Inverse Trigonometric Functions": 0,
      "Matrices and Determinants": 0,
      "Continuity and Differentiability": 0,
      "Application of Derivatives": 0,
      "Integrals": 0,
      "Application of Integrals": 0,
      "Differential Equations": 0,
      "Vector Algebra and 3D Geometry": 0,
      "Probability and LPP": 0
    },
    "milestones": {}
  },
  {
    "rollNo": 2,
    "name": "Supriya",
    "phone": "9599540886",
    "email": "supriya@gmail.com",
    "scores": {
      "Solutions": 0,
      "Electrochemistry": 0,
      "Chemical Kinetics": 0,
      "d- and f-Block": 0,
      "Coordination Compounds": 0,
      "Haloalkanes and Haloarenes": 0,
      "Alcohols Phenols and Ethers": 0,
      "Aldehydes Ketones and Carboxylic Acids": 0,
      "Amines": 0,
      "Biomolecules": 0,
      "Electrostatics": 0,
      "Current Electricity": 0,
      "Magnetic Effects of Current": 0,
      "Electromagnetic Induction and AC": 0,
      "Electromagnetic Waves": 0,
      "Ray Optics and Optical Instruments": 0,
      "Wave Optics": 0,
      "Dual Nature of Matter": 0,
      "Atoms and Nuclei": 0,
      "Electronic Devices": 0,
      "Relations and Functions": 0,
      "Inverse Trigonometric Functions": 0,
      "Matrices and Determinants": 0,
      "Continuity and Differentiability": 0,
      "Application of Derivatives": 0,
      "Integrals": 0,
      "Application of Integrals": 0,
      "Differential Equations": 0,
      "Vector Algebra and 3D Geometry": 0,
      "Probability and LPP": 0
    },
    "milestones": {}
  },
  {
    "rollNo": 3,
    "name": "Vanshika",
    "phone": "8506061212",
    "email": "vanshika@gmail.com",
    "scores": {
      "Solutions": 0,
      "Electrochemistry": 0,
      "Chemical Kinetics": 0,
      "d- and f-Block": 0,
      "Coordination Compounds": 0,
      "Haloalkanes and Haloarenes": 0,
      "Alcohols Phenols and Ethers": 0,
      "Aldehydes Ketones and Carboxylic Acids": 0,
      "Amines": 0,
      "Biomolecules": 0,
      "Electrostatics": 0,
      "Current Electricity": 0,
      "Magnetic Effects of Current": 0,
      "Electromagnetic Induction and AC": 0,
      "Electromagnetic Waves": 0,
      "Ray Optics and Optical Instruments": 0,
      "Wave Optics": 0,
      "Dual Nature of Matter": 0,
      "Atoms and Nuclei": 0,
      "Electronic Devices": 0,
      "Relations and Functions": 0,
      "Inverse Trigonometric Functions": 0,
      "Matrices and Determinants": 0,
      "Continuity and Differentiability": 0,
      "Application of Derivatives": 0,
      "Integrals": 0,
      "Application of Integrals": 0,
      "Differential Equations": 0,
      "Vector Algebra and 3D Geometry": 0,
      "Probability and LPP": 0
    },
    "milestones": {}
  },
  {
    "rollNo": 4,
    "name": "Jai Kumar",
    "phone": "9555783802",
    "email": "jai.kumar@gmail.com",
    "scores": {
      "Solutions": 0,
      "Electrochemistry": 0,
      "Chemical Kinetics": 0,
      "d- and f-Block": 0,
      "Coordination Compounds": 0,
      "Haloalkanes and Haloarenes": 0,
      "Alcohols Phenols and Ethers": 0,
      "Aldehydes Ketones and Carboxylic Acids": 0,
      "Amines": 0,
      "Biomolecules": 0,
      "Electrostatics": 0,
      "Current Electricity": 0,
      "Magnetic Effects of Current": 0,
      "Electromagnetic Induction and AC": 0,
      "Electromagnetic Waves": 0,
      "Ray Optics and Optical Instruments": 0,
      "Wave Optics": 0,
      "Dual Nature of Matter": 0,
      "Atoms and Nuclei": 0,
      "Electronic Devices": 0,
      "Relations and Functions": 0,
      "Inverse Trigonometric Functions": 0,
      "Matrices and Determinants": 0,
      "Continuity and Differentiability": 0,
      "Application of Derivatives": 0,
      "Integrals": 0,
      "Application of Integrals": 0,
      "Differential Equations": 0,
      "Vector Algebra and 3D Geometry": 0,
      "Probability and LPP": 0
    },
    "milestones": {}
  },
  {
    "rollNo": 5,
    "name": "Aditya Prasad",
    "phone": "7678164362",
    "email": "aditya.prasad@gmail.com",
    "scores": {
      "Solutions": 0,
      "Electrochemistry": 0,
      "Chemical Kinetics": 0,
      "d- and f-Block": 0,
      "Coordination Compounds": 0,
      "Haloalkanes and Haloarenes": 0,
      "Alcohols Phenols and Ethers": 0,
      "Aldehydes Ketones and Carboxylic Acids": 0,
      "Amines": 0,
      "Biomolecules": 0,
      "Electrostatics": 0,
      "Current Electricity": 0,
      "Magnetic Effects of Current": 0,
      "Electromagnetic Induction and AC": 0,
      "Electromagnetic Waves": 0,
      "Ray Optics and Optical Instruments": 0,
      "Wave Optics": 0,
      "Dual Nature of Matter": 0,
      "Atoms and Nuclei": 0,
      "Electronic Devices": 0,
      "Relations and Functions": 0,
      "Inverse Trigonometric Functions": 0,
      "Matrices and Determinants": 0,
      "Continuity and Differentiability": 0,
      "Application of Derivatives": 0,
      "Integrals": 0,
      "Application of Integrals": 0,
      "Differential Equations": 0,
      "Vector Algebra and 3D Geometry": 0,
      "Probability and LPP": 0
    },
    "milestones": {}
  },
  {
    "rollNo": 6,
    "name": "Aarav Gupta",
    "phone": "8383904995",
    "email": "aarav.gupta@gmail.com",
    "scores": {
      "Solutions": 0,
      "Electrochemistry": 0,
      "Chemical Kinetics": 0,
      "d- and f-Block": 0,
      "Coordination Compounds": 0,
      "Haloalkanes and Haloarenes": 0,
      "Alcohols Phenols and Ethers": 0,
      "Aldehydes Ketones and Carboxylic Acids": 0,
      "Amines": 0,
      "Biomolecules": 0,
      "Electrostatics": 0,
      "Current Electricity": 0,
      "Magnetic Effects of Current": 0,
      "Electromagnetic Induction and AC": 0,
      "Electromagnetic Waves": 0,
      "Ray Optics and Optical Instruments": 0,
      "Wave Optics": 0,
      "Dual Nature of Matter": 0,
      "Atoms and Nuclei": 0,
      "Electronic Devices": 0,
      "Relations and Functions": 0,
      "Inverse Trigonometric Functions": 0,
      "Matrices and Determinants": 0,
      "Continuity and Differentiability": 0,
      "Application of Derivatives": 0,
      "Integrals": 0,
      "Application of Integrals": 0,
      "Differential Equations": 0,
      "Vector Algebra and 3D Geometry": 0,
      "Probability and LPP": 0
    },
    "milestones": {}
  },
  {
    "rollNo": 7,
    "name": "Shashwat Tiwari",
    "phone": "9718462276",
    "email": "shashwat.tiwari@gmail.com",
    "scores": {
      "Solutions": 0,
      "Electrochemistry": 0,
      "Chemical Kinetics": 0,
      "d- and f-Block": 0,
      "Coordination Compounds": 0,
      "Haloalkanes and Haloarenes": 0,
      "Alcohols Phenols and Ethers": 0,
      "Aldehydes Ketones and Carboxylic Acids": 0,
      "Amines": 0,
      "Biomolecules": 0,
      "Electrostatics": 0,
      "Current Electricity": 0,
      "Magnetic Effects of Current": 0,
      "Electromagnetic Induction and AC": 0,
      "Electromagnetic Waves": 0,
      "Ray Optics and Optical Instruments": 0,
      "Wave Optics": 0,
      "Dual Nature of Matter": 0,
      "Atoms and Nuclei": 0,
      "Electronic Devices": 0,
      "Relations and Functions": 0,
      "Inverse Trigonometric Functions": 0,
      "Matrices and Determinants": 0,
      "Continuity and Differentiability": 0,
      "Application of Derivatives": 0,
      "Integrals": 0,
      "Application of Integrals": 0,
      "Differential Equations": 0,
      "Vector Algebra and 3D Geometry": 0,
      "Probability and LPP": 0
    },
    "milestones": {}
  },
  {
    "rollNo": 8,
    "name": "Udbhav Dalmia",
    "phone": "8178109588",
    "email": "udbhav.dalmia@gmail.com",
    "scores": {
      "Solutions": 0,
      "Electrochemistry": 75,
      "Chemical Kinetics": 0,
      "d- and f-Block": 0,
      "Coordination Compounds": 0,
      "Haloalkanes and Haloarenes": 0,
      "Alcohols Phenols and Ethers": 0,
      "Aldehydes Ketones and Carboxylic Acids": 0,
      "Amines": 0,
      "Biomolecules": 0,
      "Electrostatics": 0,
      "Current Electricity": 0,
      "Magnetic Effects of Current": 0,
      "Electromagnetic Induction and AC": 0,
      "Electromagnetic Waves": 0,
      "Ray Optics and Optical Instruments": 0,
      "Wave Optics": 0,
      "Dual Nature of Matter": 0,
      "Atoms and Nuclei": 0,
      "Electronic Devices": 0,
      "Relations and Functions": 0,
      "Inverse Trigonometric Functions": 0,
      "Matrices and Determinants": 0,
      "Continuity and Differentiability": 0,
      "Application of Derivatives": 0,
      "Integrals": 0,
      "Application of Integrals": 0,
      "Differential Equations": 0,
      "Vector Algebra and 3D Geometry": 0,
      "Probability and LPP": 0
    },
    "milestones": {
      "Electrochemistry": [
        true,
        true,
        true,
        false
      ]
    }
  },
  {
    "rollNo": 9,
    "name": "Simran Pokhriyal",
    "phone": "9354667018",
    "email": "simran.pokhriyal@gmail.com",
    "scores": {
      "Solutions": 0,
      "Electrochemistry": 0,
      "Chemical Kinetics": 0,
      "d- and f-Block": 0,
      "Coordination Compounds": 0,
      "Haloalkanes and Haloarenes": 0,
      "Alcohols Phenols and Ethers": 0,
      "Aldehydes Ketones and Carboxylic Acids": 0,
      "Amines": 0,
      "Biomolecules": 0,
      "Electrostatics": 0,
      "Current Electricity": 0,
      "Magnetic Effects of Current": 0,
      "Electromagnetic Induction and AC": 0,
      "Electromagnetic Waves": 0,
      "Ray Optics and Optical Instruments": 0,
      "Wave Optics": 0,
      "Dual Nature of Matter": 0,
      "Atoms and Nuclei": 0,
      "Electronic Devices": 0,
      "Relations and Functions": 0,
      "Inverse Trigonometric Functions": 0,
      "Matrices and Determinants": 0,
      "Continuity and Differentiability": 0,
      "Application of Derivatives": 0,
      "Integrals": 0,
      "Application of Integrals": 0,
      "Differential Equations": 0,
      "Vector Algebra and 3D Geometry": 0,
      "Probability and LPP": 0
    },
    "milestones": {}
  },
  {
    "rollNo": 10,
    "name": "Ishank",
    "phone": "7011157797",
    "email": "ishank@gmail.com",
    "scores": {
      "Solutions": 0,
      "Electrochemistry": 0,
      "Chemical Kinetics": 0,
      "d- and f-Block": 0,
      "Coordination Compounds": 0,
      "Haloalkanes and Haloarenes": 0,
      "Alcohols Phenols and Ethers": 0,
      "Aldehydes Ketones and Carboxylic Acids": 0,
      "Amines": 0,
      "Biomolecules": 0,
      "Electrostatics": 0,
      "Current Electricity": 0,
      "Magnetic Effects of Current": 0,
      "Electromagnetic Induction and AC": 0,
      "Electromagnetic Waves": 0,
      "Ray Optics and Optical Instruments": 0,
      "Wave Optics": 0,
      "Dual Nature of Matter": 0,
      "Atoms and Nuclei": 0,
      "Electronic Devices": 0,
      "Relations and Functions": 0,
      "Inverse Trigonometric Functions": 0,
      "Matrices and Determinants": 0,
      "Continuity and Differentiability": 0,
      "Application of Derivatives": 0,
      "Integrals": 0,
      "Application of Integrals": 0,
      "Differential Equations": 0,
      "Vector Algebra and 3D Geometry": 0,
      "Probability and LPP": 0
    },
    "milestones": {}
  },
  {
    "rollNo": 11,
    "name": "Aditya Prajapati",
    "phone": "9213819186",
    "email": "aditya.prajapati@gmail.com",
    "scores": {
      "Solutions": 0,
      "Electrochemistry": 0,
      "Chemical Kinetics": 0,
      "d- and f-Block": 0,
      "Coordination Compounds": 0,
      "Haloalkanes and Haloarenes": 0,
      "Alcohols Phenols and Ethers": 0,
      "Aldehydes Ketones and Carboxylic Acids": 0,
      "Amines": 0,
      "Biomolecules": 0,
      "Electrostatics": 0,
      "Current Electricity": 0,
      "Magnetic Effects of Current": 0,
      "Electromagnetic Induction and AC": 0,
      "Electromagnetic Waves": 0,
      "Ray Optics and Optical Instruments": 0,
      "Wave Optics": 0,
      "Dual Nature of Matter": 0,
      "Atoms and Nuclei": 0,
      "Electronic Devices": 0,
      "Relations and Functions": 0,
      "Inverse Trigonometric Functions": 0,
      "Matrices and Determinants": 0,
      "Continuity and Differentiability": 0,
      "Application of Derivatives": 0,
      "Integrals": 0,
      "Application of Integrals": 0,
      "Differential Equations": 0,
      "Vector Algebra and 3D Geometry": 0,
      "Probability and LPP": 0
    },
    "milestones": {}
  },
  {
    "rollNo": 12,
    "name": "Pragun Sharma",
    "phone": "8800862176",
    "email": "pragun.sharma@gmail.com",
    "scores": {
      "Solutions": 0,
      "Electrochemistry": 0,
      "Chemical Kinetics": 0,
      "d- and f-Block": 0,
      "Coordination Compounds": 0,
      "Haloalkanes and Haloarenes": 0,
      "Alcohols Phenols and Ethers": 0,
      "Aldehydes Ketones and Carboxylic Acids": 0,
      "Amines": 0,
      "Biomolecules": 0,
      "Electrostatics": 0,
      "Current Electricity": 0,
      "Magnetic Effects of Current": 0,
      "Electromagnetic Induction and AC": 0,
      "Electromagnetic Waves": 0,
      "Ray Optics and Optical Instruments": 0,
      "Wave Optics": 0,
      "Dual Nature of Matter": 0,
      "Atoms and Nuclei": 0,
      "Electronic Devices": 0,
      "Relations and Functions": 0,
      "Inverse Trigonometric Functions": 0,
      "Matrices and Determinants": 0,
      "Continuity and Differentiability": 0,
      "Application of Derivatives": 0,
      "Integrals": 0,
      "Application of Integrals": 0,
      "Differential Equations": 0,
      "Vector Algebra and 3D Geometry": 0,
      "Probability and LPP": 0
    },
    "milestones": {}
  },
  {
    "rollNo": 13,
    "name": "Aryan Dubey",
    "phone": "7703824656",
    "email": "aryan.dubey@gmail.com",
    "scores": {
      "Solutions": 0,
      "Electrochemistry": 0,
      "Chemical Kinetics": 0,
      "d- and f-Block": 0,
      "Coordination Compounds": 0,
      "Haloalkanes and Haloarenes": 0,
      "Alcohols Phenols and Ethers": 0,
      "Aldehydes Ketones and Carboxylic Acids": 0,
      "Amines": 0,
      "Biomolecules": 0,
      "Electrostatics": 0,
      "Current Electricity": 0,
      "Magnetic Effects of Current": 0,
      "Electromagnetic Induction and AC": 0,
      "Electromagnetic Waves": 0,
      "Ray Optics and Optical Instruments": 0,
      "Wave Optics": 0,
      "Dual Nature of Matter": 0,
      "Atoms and Nuclei": 0,
      "Electronic Devices": 0,
      "Relations and Functions": 0,
      "Inverse Trigonometric Functions": 0,
      "Matrices and Determinants": 0,
      "Continuity and Differentiability": 0,
      "Application of Derivatives": 0,
      "Integrals": 0,
      "Application of Integrals": 0,
      "Differential Equations": 0,
      "Vector Algebra and 3D Geometry": 0,
      "Probability and LPP": 0
    },
    "milestones": {}
  },
  {
    "rollNo": 14,
    "name": "Manan Nimesh",
    "phone": "8860235111",
    "email": "manan.nimesh@gmail.com",
    "scores": {
      "Solutions": 0,
      "Electrochemistry": 0,
      "Chemical Kinetics": 0,
      "d- and f-Block": 0,
      "Coordination Compounds": 0,
      "Haloalkanes and Haloarenes": 0,
      "Alcohols Phenols and Ethers": 0,
      "Aldehydes Ketones and Carboxylic Acids": 0,
      "Amines": 0,
      "Biomolecules": 0,
      "Electrostatics": 0,
      "Current Electricity": 0,
      "Magnetic Effects of Current": 0,
      "Electromagnetic Induction and AC": 0,
      "Electromagnetic Waves": 0,
      "Ray Optics and Optical Instruments": 0,
      "Wave Optics": 0,
      "Dual Nature of Matter": 0,
      "Atoms and Nuclei": 0,
      "Electronic Devices": 0,
      "Relations and Functions": 0,
      "Inverse Trigonometric Functions": 0,
      "Matrices and Determinants": 0,
      "Continuity and Differentiability": 0,
      "Application of Derivatives": 0,
      "Integrals": 0,
      "Application of Integrals": 0,
      "Differential Equations": 0,
      "Vector Algebra and 3D Geometry": 0,
      "Probability and LPP": 0
    },
    "milestones": {}
  },
  {
    "rollNo": 15,
    "name": "Siddharth",
    "phone": "9267921428",
    "email": "siddharth@gmail.com",
    "scores": {
      "Solutions": 0,
      "Electrochemistry": 0,
      "Chemical Kinetics": 0,
      "d- and f-Block": 0,
      "Coordination Compounds": 0,
      "Haloalkanes and Haloarenes": 0,
      "Alcohols Phenols and Ethers": 0,
      "Aldehydes Ketones and Carboxylic Acids": 0,
      "Amines": 0,
      "Biomolecules": 0,
      "Electrostatics": 0,
      "Current Electricity": 0,
      "Magnetic Effects of Current": 0,
      "Electromagnetic Induction and AC": 0,
      "Electromagnetic Waves": 0,
      "Ray Optics and Optical Instruments": 0,
      "Wave Optics": 0,
      "Dual Nature of Matter": 0,
      "Atoms and Nuclei": 0,
      "Electronic Devices": 0,
      "Relations and Functions": 0,
      "Inverse Trigonometric Functions": 0,
      "Matrices and Determinants": 0,
      "Continuity and Differentiability": 0,
      "Application of Derivatives": 0,
      "Integrals": 0,
      "Application of Integrals": 0,
      "Differential Equations": 0,
      "Vector Algebra and 3D Geometry": 0,
      "Probability and LPP": 0
    },
    "milestones": {}
  },
  {
    "rollNo": 16,
    "name": "Adarsh Patel",
    "phone": "9355323047",
    "email": "adarsh.patel@gmail.com",
    "scores": {
      "Solutions": 0,
      "Electrochemistry": 0,
      "Chemical Kinetics": 0,
      "d- and f-Block": 0,
      "Coordination Compounds": 0,
      "Haloalkanes and Haloarenes": 0,
      "Alcohols Phenols and Ethers": 0,
      "Aldehydes Ketones and Carboxylic Acids": 0,
      "Amines": 0,
      "Biomolecules": 0,
      "Electrostatics": 0,
      "Current Electricity": 0,
      "Magnetic Effects of Current": 0,
      "Electromagnetic Induction and AC": 0,
      "Electromagnetic Waves": 0,
      "Ray Optics and Optical Instruments": 0,
      "Wave Optics": 0,
      "Dual Nature of Matter": 0,
      "Atoms and Nuclei": 0,
      "Electronic Devices": 0,
      "Relations and Functions": 0,
      "Inverse Trigonometric Functions": 0,
      "Matrices and Determinants": 0,
      "Continuity and Differentiability": 0,
      "Application of Derivatives": 0,
      "Integrals": 0,
      "Application of Integrals": 0,
      "Differential Equations": 0,
      "Vector Algebra and 3D Geometry": 0,
      "Probability and LPP": 0
    },
    "milestones": {}
  },
  {
    "rollNo": 17,
    "name": "Kanishk",
    "phone": "9873039704",
    "email": "kanishk@gmail.com",
    "scores": {
      "Solutions": 0,
      "Electrochemistry": 0,
      "Chemical Kinetics": 0,
      "d- and f-Block": 0,
      "Coordination Compounds": 0,
      "Haloalkanes and Haloarenes": 0,
      "Alcohols Phenols and Ethers": 0,
      "Aldehydes Ketones and Carboxylic Acids": 0,
      "Amines": 0,
      "Biomolecules": 0,
      "Electrostatics": 0,
      "Current Electricity": 0,
      "Magnetic Effects of Current": 0,
      "Electromagnetic Induction and AC": 0,
      "Electromagnetic Waves": 0,
      "Ray Optics and Optical Instruments": 0,
      "Wave Optics": 0,
      "Dual Nature of Matter": 0,
      "Atoms and Nuclei": 0,
      "Electronic Devices": 0,
      "Relations and Functions": 0,
      "Inverse Trigonometric Functions": 0,
      "Matrices and Determinants": 0,
      "Continuity and Differentiability": 0,
      "Application of Derivatives": 0,
      "Integrals": 0,
      "Application of Integrals": 0,
      "Differential Equations": 0,
      "Vector Algebra and 3D Geometry": 0,
      "Probability and LPP": 0
    },
    "milestones": {}
  },
  {
    "rollNo": 18,
    "name": "Kirti",
    "phone": "8595741151",
    "email": "kirti@gmail.com",
    "scores": {
      "Solutions": 0,
      "Electrochemistry": 0,
      "Chemical Kinetics": 0,
      "d- and f-Block": 0,
      "Coordination Compounds": 0,
      "Haloalkanes and Haloarenes": 0,
      "Alcohols Phenols and Ethers": 0,
      "Aldehydes Ketones and Carboxylic Acids": 0,
      "Amines": 0,
      "Biomolecules": 0,
      "Electrostatics": 0,
      "Current Electricity": 0,
      "Magnetic Effects of Current": 0,
      "Electromagnetic Induction and AC": 0,
      "Electromagnetic Waves": 0,
      "Ray Optics and Optical Instruments": 0,
      "Wave Optics": 0,
      "Dual Nature of Matter": 0,
      "Atoms and Nuclei": 0,
      "Electronic Devices": 0,
      "Relations and Functions": 0,
      "Inverse Trigonometric Functions": 0,
      "Matrices and Determinants": 0,
      "Continuity and Differentiability": 0,
      "Application of Derivatives": 0,
      "Integrals": 0,
      "Application of Integrals": 0,
      "Differential Equations": 0,
      "Vector Algebra and 3D Geometry": 0,
      "Probability and LPP": 0
    },
    "milestones": {}
  },
  {
    "rollNo": 19,
    "name": "Ansh Kumar",
    "phone": "8595048032",
    "email": "ansh.kumar@gmail.com",
    "scores": {
      "Solutions": 0,
      "Electrochemistry": 0,
      "Chemical Kinetics": 0,
      "d- and f-Block": 0,
      "Coordination Compounds": 0,
      "Haloalkanes and Haloarenes": 0,
      "Alcohols Phenols and Ethers": 0,
      "Aldehydes Ketones and Carboxylic Acids": 0,
      "Amines": 0,
      "Biomolecules": 0,
      "Electrostatics": 0,
      "Current Electricity": 0,
      "Magnetic Effects of Current": 0,
      "Electromagnetic Induction and AC": 0,
      "Electromagnetic Waves": 0,
      "Ray Optics and Optical Instruments": 0,
      "Wave Optics": 0,
      "Dual Nature of Matter": 0,
      "Atoms and Nuclei": 0,
      "Electronic Devices": 0,
      "Relations and Functions": 0,
      "Inverse Trigonometric Functions": 0,
      "Matrices and Determinants": 0,
      "Continuity and Differentiability": 0,
      "Application of Derivatives": 0,
      "Integrals": 0,
      "Application of Integrals": 0,
      "Differential Equations": 0,
      "Vector Algebra and 3D Geometry": 0,
      "Probability and LPP": 0
    },
    "milestones": {}
  },
  {
    "rollNo": 20,
    "name": "Dev Rathore",
    "phone": "9211487571",
    "email": "dev.rathore@gmail.com",
    "scores": {
      "Solutions": 0,
      "Electrochemistry": 0,
      "Chemical Kinetics": 0,
      "d- and f-Block": 0,
      "Coordination Compounds": 0,
      "Haloalkanes and Haloarenes": 0,
      "Alcohols Phenols and Ethers": 0,
      "Aldehydes Ketones and Carboxylic Acids": 0,
      "Amines": 0,
      "Biomolecules": 0,
      "Electrostatics": 0,
      "Current Electricity": 0,
      "Magnetic Effects of Current": 0,
      "Electromagnetic Induction and AC": 0,
      "Electromagnetic Waves": 0,
      "Ray Optics and Optical Instruments": 0,
      "Wave Optics": 0,
      "Dual Nature of Matter": 0,
      "Atoms and Nuclei": 0,
      "Electronic Devices": 0,
      "Relations and Functions": 0,
      "Inverse Trigonometric Functions": 0,
      "Matrices and Determinants": 0,
      "Continuity and Differentiability": 0,
      "Application of Derivatives": 0,
      "Integrals": 0,
      "Application of Integrals": 0,
      "Differential Equations": 0,
      "Vector Algebra and 3D Geometry": 0,
      "Probability and LPP": 0
    },
    "milestones": {}
  },
  {
    "rollNo": 21,
    "name": "Sidhant Gupta",
    "phone": "7633925835",
    "email": "sidhant.gupta@gmail.com",
    "scores": {
      "Solutions": 0,
      "Electrochemistry": 0,
      "Chemical Kinetics": 0,
      "d- and f-Block": 0,
      "Coordination Compounds": 0,
      "Haloalkanes and Haloarenes": 0,
      "Alcohols Phenols and Ethers": 0,
      "Aldehydes Ketones and Carboxylic Acids": 0,
      "Amines": 0,
      "Biomolecules": 0,
      "Electrostatics": 0,
      "Current Electricity": 0,
      "Magnetic Effects of Current": 0,
      "Electromagnetic Induction and AC": 0,
      "Electromagnetic Waves": 0,
      "Ray Optics and Optical Instruments": 0,
      "Wave Optics": 0,
      "Dual Nature of Matter": 0,
      "Atoms and Nuclei": 0,
      "Electronic Devices": 0,
      "Relations and Functions": 0,
      "Inverse Trigonometric Functions": 0,
      "Matrices and Determinants": 0,
      "Continuity and Differentiability": 0,
      "Application of Derivatives": 0,
      "Integrals": 0,
      "Application of Integrals": 0,
      "Differential Equations": 0,
      "Vector Algebra and 3D Geometry": 0,
      "Probability and LPP": 0
    },
    "milestones": {}
  },
  {
    "rollNo": 22,
    "name": "Komal Mehra",
    "phone": "8588015525",
    "email": "komal.mehra@gmail.com",
    "scores": {
      "Solutions": 0,
      "Electrochemistry": 0,
      "Chemical Kinetics": 0,
      "d- and f-Block": 0,
      "Coordination Compounds": 0,
      "Haloalkanes and Haloarenes": 0,
      "Alcohols Phenols and Ethers": 0,
      "Aldehydes Ketones and Carboxylic Acids": 0,
      "Amines": 0,
      "Biomolecules": 0,
      "Electrostatics": 0,
      "Current Electricity": 0,
      "Magnetic Effects of Current": 0,
      "Electromagnetic Induction and AC": 0,
      "Electromagnetic Waves": 0,
      "Ray Optics and Optical Instruments": 0,
      "Wave Optics": 0,
      "Dual Nature of Matter": 0,
      "Atoms and Nuclei": 0,
      "Electronic Devices": 0,
      "Relations and Functions": 0,
      "Inverse Trigonometric Functions": 0,
      "Matrices and Determinants": 0,
      "Continuity and Differentiability": 0,
      "Application of Derivatives": 0,
      "Integrals": 0,
      "Application of Integrals": 0,
      "Differential Equations": 0,
      "Vector Algebra and 3D Geometry": 0,
      "Probability and LPP": 0
    },
    "milestones": {}
  },
  {
    "rollNo": 23,
    "name": "Viraj Dagar",
    "phone": "9540836788",
    "email": "viraj.dagar@gmail.com",
    "scores": {
      "Solutions": 0,
      "Electrochemistry": 0,
      "Chemical Kinetics": 0,
      "d- and f-Block": 0,
      "Coordination Compounds": 0,
      "Haloalkanes and Haloarenes": 0,
      "Alcohols Phenols and Ethers": 0,
      "Aldehydes Ketones and Carboxylic Acids": 0,
      "Amines": 0,
      "Biomolecules": 0,
      "Electrostatics": 0,
      "Current Electricity": 0,
      "Magnetic Effects of Current": 0,
      "Electromagnetic Induction and AC": 0,
      "Electromagnetic Waves": 0,
      "Ray Optics and Optical Instruments": 0,
      "Wave Optics": 0,
      "Dual Nature of Matter": 0,
      "Atoms and Nuclei": 0,
      "Electronic Devices": 0,
      "Relations and Functions": 0,
      "Inverse Trigonometric Functions": 0,
      "Matrices and Determinants": 0,
      "Continuity and Differentiability": 0,
      "Application of Derivatives": 0,
      "Integrals": 0,
      "Application of Integrals": 0,
      "Differential Equations": 0,
      "Vector Algebra and 3D Geometry": 0,
      "Probability and LPP": 0
    },
    "milestones": {}
  },
  {
    "rollNo": 24,
    "name": "Rakesh Kumar Rai",
    "phone": "8178777178",
    "email": "rakesh.rai@gmail.com",
    "scores": {
      "Solutions": 0,
      "Electrochemistry": 0,
      "Chemical Kinetics": 0,
      "d- and f-Block": 0,
      "Coordination Compounds": 0,
      "Haloalkanes and Haloarenes": 0,
      "Alcohols Phenols and Ethers": 0,
      "Aldehydes Ketones and Carboxylic Acids": 0,
      "Amines": 0,
      "Biomolecules": 0,
      "Electrostatics": 0,
      "Current Electricity": 0,
      "Magnetic Effects of Current": 0,
      "Electromagnetic Induction and AC": 0,
      "Electromagnetic Waves": 0,
      "Ray Optics and Optical Instruments": 0,
      "Wave Optics": 0,
      "Dual Nature of Matter": 0,
      "Atoms and Nuclei": 0,
      "Electronic Devices": 0,
      "Relations and Functions": 0,
      "Inverse Trigonometric Functions": 0,
      "Matrices and Determinants": 0,
      "Continuity and Differentiability": 0,
      "Application of Derivatives": 0,
      "Integrals": 0,
      "Application of Integrals": 0,
      "Differential Equations": 0,
      "Vector Algebra and 3D Geometry": 0,
      "Probability and LPP": 0
    },
    "milestones": {}
  },
  {
    "rollNo": 25,
    "name": "Lucky",
    "phone": "9871749320",
    "email": "lucky@gmail.com",
    "scores": {
      "Solutions": 0,
      "Electrochemistry": 0,
      "Chemical Kinetics": 0,
      "d- and f-Block": 0,
      "Coordination Compounds": 0,
      "Haloalkanes and Haloarenes": 0,
      "Alcohols Phenols and Ethers": 0,
      "Aldehydes Ketones and Carboxylic Acids": 0,
      "Amines": 0,
      "Biomolecules": 0,
      "Electrostatics": 0,
      "Current Electricity": 0,
      "Magnetic Effects of Current": 0,
      "Electromagnetic Induction and AC": 0,
      "Electromagnetic Waves": 0,
      "Ray Optics and Optical Instruments": 0,
      "Wave Optics": 0,
      "Dual Nature of Matter": 0,
      "Atoms and Nuclei": 0,
      "Electronic Devices": 0,
      "Relations and Functions": 0,
      "Inverse Trigonometric Functions": 0,
      "Matrices and Determinants": 0,
      "Continuity and Differentiability": 0,
      "Application of Derivatives": 0,
      "Integrals": 0,
      "Application of Integrals": 0,
      "Differential Equations": 0,
      "Vector Algebra and 3D Geometry": 0,
      "Probability and LPP": 0
    },
    "milestones": {}
  },
  {
    "rollNo": 26,
    "name": "Prince",
    "phone": "9891240667",
    "email": "prince@gmail.com",
    "scores": {
      "Solutions": 0,
      "Electrochemistry": 0,
      "Chemical Kinetics": 0,
      "d- and f-Block": 0,
      "Coordination Compounds": 0,
      "Haloalkanes and Haloarenes": 0,
      "Alcohols Phenols and Ethers": 0,
      "Aldehydes Ketones and Carboxylic Acids": 0,
      "Amines": 0,
      "Biomolecules": 0,
      "Electrostatics": 0,
      "Current Electricity": 0,
      "Magnetic Effects of Current": 0,
      "Electromagnetic Induction and AC": 0,
      "Electromagnetic Waves": 0,
      "Ray Optics and Optical Instruments": 0,
      "Wave Optics": 0,
      "Dual Nature of Matter": 0,
      "Atoms and Nuclei": 0,
      "Electronic Devices": 0,
      "Relations and Functions": 0,
      "Inverse Trigonometric Functions": 0,
      "Matrices and Determinants": 0,
      "Continuity and Differentiability": 0,
      "Application of Derivatives": 0,
      "Integrals": 0,
      "Application of Integrals": 0,
      "Differential Equations": 0,
      "Vector Algebra and 3D Geometry": 0,
      "Probability and LPP": 0
    },
    "milestones": {}
  },
  {
    "rollNo": 27,
    "name": "Gaurav",
    "phone": "7042508621",
    "email": "gaurav@gmail.com",
    "scores": {
      "Solutions": 0,
      "Electrochemistry": 0,
      "Chemical Kinetics": 0,
      "d- and f-Block": 0,
      "Coordination Compounds": 0,
      "Haloalkanes and Haloarenes": 0,
      "Alcohols Phenols and Ethers": 0,
      "Aldehydes Ketones and Carboxylic Acids": 0,
      "Amines": 0,
      "Biomolecules": 0,
      "Electrostatics": 0,
      "Current Electricity": 0,
      "Magnetic Effects of Current": 0,
      "Electromagnetic Induction and AC": 0,
      "Electromagnetic Waves": 0,
      "Ray Optics and Optical Instruments": 0,
      "Wave Optics": 0,
      "Dual Nature of Matter": 0,
      "Atoms and Nuclei": 0,
      "Electronic Devices": 0,
      "Relations and Functions": 0,
      "Inverse Trigonometric Functions": 0,
      "Matrices and Determinants": 0,
      "Continuity and Differentiability": 0,
      "Application of Derivatives": 0,
      "Integrals": 0,
      "Application of Integrals": 0,
      "Differential Equations": 0,
      "Vector Algebra and 3D Geometry": 0,
      "Probability and LPP": 0
    },
    "milestones": {}
  },
  {
    "rollNo": 28,
    "name": "Aneesh Kumar",
    "phone": "8651835743",
    "email": "aneesh.kumar@gmail.com",
    "scores": {
      "Solutions": 0,
      "Electrochemistry": 0,
      "Chemical Kinetics": 0,
      "d- and f-Block": 0,
      "Coordination Compounds": 0,
      "Haloalkanes and Haloarenes": 0,
      "Alcohols Phenols and Ethers": 0,
      "Aldehydes Ketones and Carboxylic Acids": 0,
      "Amines": 0,
      "Biomolecules": 0,
      "Electrostatics": 0,
      "Current Electricity": 0,
      "Magnetic Effects of Current": 0,
      "Electromagnetic Induction and AC": 0,
      "Electromagnetic Waves": 0,
      "Ray Optics and Optical Instruments": 0,
      "Wave Optics": 0,
      "Dual Nature of Matter": 0,
      "Atoms and Nuclei": 0,
      "Electronic Devices": 0,
      "Relations and Functions": 0,
      "Inverse Trigonometric Functions": 0,
      "Matrices and Determinants": 0,
      "Continuity and Differentiability": 0,
      "Application of Derivatives": 0,
      "Integrals": 0,
      "Application of Integrals": 0,
      "Differential Equations": 0,
      "Vector Algebra and 3D Geometry": 0,
      "Probability and LPP": 0
    },
    "milestones": {}
  },
  {
    "rollNo": 29,
    "name": "Anshuman Tripathi",
    "phone": "8076237923",
    "email": "anshuman.tripathi@gmail.com",
    "scores": {
      "Solutions": 0,
      "Electrochemistry": 0,
      "Chemical Kinetics": 0,
      "d- and f-Block": 0,
      "Coordination Compounds": 0,
      "Haloalkanes and Haloarenes": 0,
      "Alcohols Phenols and Ethers": 0,
      "Aldehydes Ketones and Carboxylic Acids": 0,
      "Amines": 0,
      "Biomolecules": 0,
      "Electrostatics": 0,
      "Current Electricity": 0,
      "Magnetic Effects of Current": 0,
      "Electromagnetic Induction and AC": 0,
      "Electromagnetic Waves": 0,
      "Ray Optics and Optical Instruments": 0,
      "Wave Optics": 0,
      "Dual Nature of Matter": 0,
      "Atoms and Nuclei": 0,
      "Electronic Devices": 0,
      "Relations and Functions": 0,
      "Inverse Trigonometric Functions": 0,
      "Matrices and Determinants": 0,
      "Continuity and Differentiability": 0,
      "Application of Derivatives": 0,
      "Integrals": 0,
      "Application of Integrals": 0,
      "Differential Equations": 0,
      "Vector Algebra and 3D Geometry": 0,
      "Probability and LPP": 0
    },
    "milestones": {}
  },
  {
    "rollNo": 30,
    "name": "Yash Bisht",
    "phone": "9355753773",
    "email": "yash.bisht@gmail.com",
    "scores": {
      "Solutions": 0,
      "Electrochemistry": 0,
      "Chemical Kinetics": 0,
      "d- and f-Block": 0,
      "Coordination Compounds": 0,
      "Haloalkanes and Haloarenes": 0,
      "Alcohols Phenols and Ethers": 0,
      "Aldehydes Ketones and Carboxylic Acids": 0,
      "Amines": 0,
      "Biomolecules": 0,
      "Electrostatics": 0,
      "Current Electricity": 0,
      "Magnetic Effects of Current": 0,
      "Electromagnetic Induction and AC": 0,
      "Electromagnetic Waves": 0,
      "Ray Optics and Optical Instruments": 0,
      "Wave Optics": 0,
      "Dual Nature of Matter": 0,
      "Atoms and Nuclei": 0,
      "Electronic Devices": 0,
      "Relations and Functions": 0,
      "Inverse Trigonometric Functions": 0,
      "Matrices and Determinants": 0,
      "Continuity and Differentiability": 0,
      "Application of Derivatives": 0,
      "Integrals": 0,
      "Application of Integrals": 0,
      "Differential Equations": 0,
      "Vector Algebra and 3D Geometry": 0,
      "Probability and LPP": 0
    },
    "milestones": {}
  },
  {
    "rollNo": 31,
    "name": "Laxman",
    "phone": "9310984491",
    "email": "laxman@gmail.com",
    "scores": {
      "Solutions": 0,
      "Electrochemistry": 0,
      "Chemical Kinetics": 0,
      "d- and f-Block": 0,
      "Coordination Compounds": 0,
      "Haloalkanes and Haloarenes": 0,
      "Alcohols Phenols and Ethers": 0,
      "Aldehydes Ketones and Carboxylic Acids": 0,
      "Amines": 0,
      "Biomolecules": 0,
      "Electrostatics": 0,
      "Current Electricity": 0,
      "Magnetic Effects of Current": 0,
      "Electromagnetic Induction and AC": 0,
      "Electromagnetic Waves": 0,
      "Ray Optics and Optical Instruments": 0,
      "Wave Optics": 0,
      "Dual Nature of Matter": 0,
      "Atoms and Nuclei": 0,
      "Electronic Devices": 0,
      "Relations and Functions": 0,
      "Inverse Trigonometric Functions": 0,
      "Matrices and Determinants": 0,
      "Continuity and Differentiability": 0,
      "Application of Derivatives": 0,
      "Integrals": 0,
      "Application of Integrals": 0,
      "Differential Equations": 0,
      "Vector Algebra and 3D Geometry": 0,
      "Probability and LPP": 0
    },
    "milestones": {}
  },
  {
    "rollNo": 32,
    "name": "Parth",
    "phone": "9837168670",
    "email": "parth@gmail.com",
    "scores": {
      "Solutions": 0,
      "Electrochemistry": 0,
      "Chemical Kinetics": 0,
      "d- and f-Block": 0,
      "Coordination Compounds": 0,
      "Haloalkanes and Haloarenes": 0,
      "Alcohols Phenols and Ethers": 0,
      "Aldehydes Ketones and Carboxylic Acids": 0,
      "Amines": 0,
      "Biomolecules": 0,
      "Electrostatics": 0,
      "Current Electricity": 0,
      "Magnetic Effects of Current": 0,
      "Electromagnetic Induction and AC": 0,
      "Electromagnetic Waves": 0,
      "Ray Optics and Optical Instruments": 0,
      "Wave Optics": 0,
      "Dual Nature of Matter": 0,
      "Atoms and Nuclei": 0,
      "Electronic Devices": 0,
      "Relations and Functions": 0,
      "Inverse Trigonometric Functions": 0,
      "Matrices and Determinants": 0,
      "Continuity and Differentiability": 0,
      "Application of Derivatives": 0,
      "Integrals": 0,
      "Application of Integrals": 0,
      "Differential Equations": 0,
      "Vector Algebra and 3D Geometry": 0,
      "Probability and LPP": 0
    },
    "milestones": {}
  },
  {
    "rollNo": 33,
    "name": "Nishtha Lahoti",
    "phone": "9312102838",
    "email": "nishtha.lahoti@gmail.com",
    "scores": {
      "Solutions": 0,
      "Electrochemistry": 0,
      "Chemical Kinetics": 0,
      "d- and f-Block": 0,
      "Coordination Compounds": 0,
      "Haloalkanes and Haloarenes": 0,
      "Alcohols Phenols and Ethers": 0,
      "Aldehydes Ketones and Carboxylic Acids": 0,
      "Amines": 0,
      "Biomolecules": 0,
      "Electrostatics": 0,
      "Current Electricity": 0,
      "Magnetic Effects of Current": 0,
      "Electromagnetic Induction and AC": 0,
      "Electromagnetic Waves": 0,
      "Ray Optics and Optical Instruments": 0,
      "Wave Optics": 0,
      "Dual Nature of Matter": 0,
      "Atoms and Nuclei": 0,
      "Electronic Devices": 0,
      "Relations and Functions": 0,
      "Inverse Trigonometric Functions": 0,
      "Matrices and Determinants": 0,
      "Continuity and Differentiability": 0,
      "Application of Derivatives": 0,
      "Integrals": 0,
      "Application of Integrals": 0,
      "Differential Equations": 0,
      "Vector Algebra and 3D Geometry": 0,
      "Probability and LPP": 0
    },
    "milestones": {}
  },
  {
    "rollNo": 34,
    "name": "Aayush Mishra",
    "phone": "8860927753",
    "email": "aayush.mishra@gmail.com",
    "scores": {
      "Solutions": 0,
      "Electrochemistry": 0,
      "Chemical Kinetics": 0,
      "d- and f-Block": 0,
      "Coordination Compounds": 0,
      "Haloalkanes and Haloarenes": 0,
      "Alcohols Phenols and Ethers": 0,
      "Aldehydes Ketones and Carboxylic Acids": 0,
      "Amines": 0,
      "Biomolecules": 0,
      "Electrostatics": 0,
      "Current Electricity": 0,
      "Magnetic Effects of Current": 0,
      "Electromagnetic Induction and AC": 0,
      "Electromagnetic Waves": 0,
      "Ray Optics and Optical Instruments": 0,
      "Wave Optics": 0,
      "Dual Nature of Matter": 0,
      "Atoms and Nuclei": 0,
      "Electronic Devices": 0,
      "Relations and Functions": 0,
      "Inverse Trigonometric Functions": 0,
      "Matrices and Determinants": 0,
      "Continuity and Differentiability": 0,
      "Application of Derivatives": 0,
      "Integrals": 0,
      "Application of Integrals": 0,
      "Differential Equations": 0,
      "Vector Algebra and 3D Geometry": 0,
      "Probability and LPP": 0
    },
    "milestones": {}
  },
  {
    "rollNo": 35,
    "name": "Harshit",
    "phone": "9205943320",
    "email": "harshit@gmail.com",
    "scores": {
      "Solutions": 0,
      "Electrochemistry": 0,
      "Chemical Kinetics": 0,
      "d- and f-Block": 0,
      "Coordination Compounds": 0,
      "Haloalkanes and Haloarenes": 0,
      "Alcohols Phenols and Ethers": 0,
      "Aldehydes Ketones and Carboxylic Acids": 0,
      "Amines": 0,
      "Biomolecules": 0,
      "Electrostatics": 0,
      "Current Electricity": 0,
      "Magnetic Effects of Current": 0,
      "Electromagnetic Induction and AC": 0,
      "Electromagnetic Waves": 0,
      "Ray Optics and Optical Instruments": 0,
      "Wave Optics": 0,
      "Dual Nature of Matter": 0,
      "Atoms and Nuclei": 0,
      "Electronic Devices": 0,
      "Relations and Functions": 0,
      "Inverse Trigonometric Functions": 0,
      "Matrices and Determinants": 0,
      "Continuity and Differentiability": 0,
      "Application of Derivatives": 0,
      "Integrals": 0,
      "Application of Integrals": 0,
      "Differential Equations": 0,
      "Vector Algebra and 3D Geometry": 0,
      "Probability and LPP": 0
    },
    "milestones": {}
  },
  {
    "rollNo": 36,
    "name": "Drishti",
    "phone": "8368857795",
    "email": "drishti@gmail.com",
    "scores": {
      "Solutions": 0,
      "Electrochemistry": 0,
      "Chemical Kinetics": 0,
      "d- and f-Block": 0,
      "Coordination Compounds": 0,
      "Haloalkanes and Haloarenes": 0,
      "Alcohols Phenols and Ethers": 0,
      "Aldehydes Ketones and Carboxylic Acids": 0,
      "Amines": 0,
      "Biomolecules": 0,
      "Electrostatics": 0,
      "Current Electricity": 0,
      "Magnetic Effects of Current": 0,
      "Electromagnetic Induction and AC": 0,
      "Electromagnetic Waves": 0,
      "Ray Optics and Optical Instruments": 0,
      "Wave Optics": 0,
      "Dual Nature of Matter": 0,
      "Atoms and Nuclei": 0,
      "Electronic Devices": 0,
      "Relations and Functions": 0,
      "Inverse Trigonometric Functions": 0,
      "Matrices and Determinants": 0,
      "Continuity and Differentiability": 0,
      "Application of Derivatives": 0,
      "Integrals": 0,
      "Application of Integrals": 0,
      "Differential Equations": 0,
      "Vector Algebra and 3D Geometry": 0,
      "Probability and LPP": 0
    },
    "milestones": {}
  },
  {
    "rollNo": 37,
    "name": "Priyanshi Vahal",
    "phone": "9810297183",
    "email": "priyanshi.vahal@gmail.com",
    "scores": {
      "Solutions": 0,
      "Electrochemistry": 0,
      "Chemical Kinetics": 0,
      "d- and f-Block": 0,
      "Coordination Compounds": 0,
      "Haloalkanes and Haloarenes": 0,
      "Alcohols Phenols and Ethers": 0,
      "Aldehydes Ketones and Carboxylic Acids": 0,
      "Amines": 0,
      "Biomolecules": 0,
      "Electrostatics": 0,
      "Current Electricity": 0,
      "Magnetic Effects of Current": 0,
      "Electromagnetic Induction and AC": 0,
      "Electromagnetic Waves": 0,
      "Ray Optics and Optical Instruments": 0,
      "Wave Optics": 0,
      "Dual Nature of Matter": 0,
      "Atoms and Nuclei": 0,
      "Electronic Devices": 0,
      "Relations and Functions": 0,
      "Inverse Trigonometric Functions": 0,
      "Matrices and Determinants": 0,
      "Continuity and Differentiability": 0,
      "Application of Derivatives": 0,
      "Integrals": 0,
      "Application of Integrals": 0,
      "Differential Equations": 0,
      "Vector Algebra and 3D Geometry": 0,
      "Probability and LPP": 0
    },
    "milestones": {}
  }
]